serveai/app.py
serveai/cli.py
serveai/config.py
serveai/database.py
serveai/functions.py
serveai/middlewares.py
serveai/routes.py
serveai-0.1.0.dist-info/METADATA
serveai-0.1.0.dist-info/WHEEL
serveai-0.1.0.dist-info/RECORD
