Metadata-Version: 2.1
Name: serveai
Version: 0.1.0
Summary: A backend server for AI APIs with user management
Author: BaksiLi
Author-email: myself@baksili.codes
Requires-Python: >=3.9,<4.0
Classifier: Programming Language :: Python :: 3
Classifier: Programming Language :: Python :: 3.9
Classifier: Programming Language :: Python :: 3.10
Classifier: Programming Language :: Python :: 3.11
Requires-Dist: flask (>=2.3.2,<3.0.0)
Requires-Dist: flask-sqlalchemy (>=3.0.3,<4.0.0)
Requires-Dist: requests (>=2.30.0,<3.0.0)
